bid/SCRAP_fetching_queries.py
bid/__init__.py
bid/aw_editor.py
bid/bull_shit_hack_because_imports_dont_work_WTF.py
bid/data_source.py
bid/diagnosis.py
bid/dup_diag.py
bid/factories.py
bid/keyword_operations_base.py
bid/keyword_operations_ms.py
bid/khan01_spike.py
bid/manip.py
bid/reporting.py
bid/russian_dolls.py
bid/russian_dolls_CAPS.py
bid/store_accessor.py
bid-0.0.1.dist-info/LICENSE
bid-0.0.1.dist-info/METADATA
bid-0.0.1.dist-info/WHEEL
bid-0.0.1.dist-info/top_level.txt
bid-0.0.1.dist-info/RECORD
